merakitools/__init__.py
merakitools/console.py
merakitools/dashboardapi.py
merakitools/devices.py
merakitools/formatting_helpers.py
merakitools/main.py
merakitools/meraki_helpers.py
merakitools/mr.py
merakitools/ms.py
merakitools/msp.py
merakitools/mt.py
merakitools/mx.py
merakitools/networks.py
merakitools/orgs.py
merakitools/types.py
merakitools-0.1.11.dist-info/entry_points.txt
merakitools-0.1.11.dist-info/LICENSE.md
merakitools-0.1.11.dist-info/WHEEL
merakitools-0.1.11.dist-info/METADATA
merakitools-0.1.11.dist-info/RECORD
