Metadata-Version: 2.1
Name: merakitools
Version: 0.1.11
Summary: CLI tools for managing Meraki networks based on Typer
Author: Billy Zoellers
Author-email: billy.zoellers@mac.com
Requires-Python: >=3.9,<4.0
Classifier: Programming Language :: Python :: 3
Classifier: Programming Language :: Python :: 3.10
Classifier: Programming Language :: Python :: 3.9
Requires-Dist: meraki (>=1.22.1,<2.0.0)
Requires-Dist: typer[all] (>=0.6.1,<0.7.0)
Project-URL: documentation, https://github.com/billyzoellers/merakitools/README.md
Project-URL: source, https://github.com/billyzoellers/merakitools
Project-URL: tracker, https://github.com/billyzoellers/merakitools/issues
